CHANGES.txt
README.txt
buildout.cfg
setup.py
bootstrap/bootstrap.py
src/zope/__init__.py
src/zope.introspectorui.egg-info/PKG-INFO
src/zope.introspectorui.egg-info/SOURCES.txt
src/zope.introspectorui.egg-info/dependency_links.txt
src/zope.introspectorui.egg-info/entry_points.txt
src/zope.introspectorui.egg-info/namespace_packages.txt
src/zope.introspectorui.egg-info/not-zip-safe
src/zope.introspectorui.egg-info/requires.txt
src/zope.introspectorui.egg-info/top_level.txt
src/zope/introspectorui/README.txt
src/zope/introspectorui/__init__.py
src/zope/introspectorui/code.py
src/zope/introspectorui/code.txt
src/zope/introspectorui/configure.zcml
src/zope/introspectorui/ftesting.zcml
src/zope/introspectorui/infoprovider.py
src/zope/introspectorui/interfaces.py
src/zope/introspectorui/util.py
src/zope/introspectorui/util.txt
src/zope/introspectorui/code_templates/class.pt
src/zope/introspectorui/code_templates/file.pt
src/zope/introspectorui/code_templates/module.pt
src/zope/introspectorui/code_templates/package.pt
src/zope/introspectorui/infoprovider_templates/module.pt
src/zope/introspectorui/infoprovider_templates/object.pt
src/zope/introspectorui/infoprovider_templates/package.pt
src/zope/introspectorui/infoprovider_templates/view.pt
src/zope/introspectorui/tests/__init__.py
src/zope/introspectorui/tests/fsetup.py
src/zope/introspectorui/tests/test_all.py